smithclient/__init__.py
smithclient/client.py
smithclient-0.1.3.dist-info/METADATA
smithclient-0.1.3.dist-info/WHEEL
smithclient-0.1.3.dist-info/top_level.txt
smithclient-0.1.3.dist-info/RECORD
