Metadata-Version: 2.1
Name: smithclient
Version: 0.1.3
Summary: Monitoring Smith smithclient
Home-page: https://github.com/dangavrilin/monitoring_smithclient.git
Author: Denis Gavrilin
Author-email: dangavrilin@gmail.com
License: MIT
Platform: UNKNOWN
Requires-Dist: requests
